frozenSpider/Data_visualisation.py
frozenSpider/__init__.py
frozenSpider/spiderAlgorithmKnn.py
frozenSpider/spiderAlgorithmLR.py
frozenSpider/spiderAlgorithmLoR.py
frozenSpider/spiderAlgorithmResources.py
frozenSpider/spiderAlgorithms.py
frozenSpider/spiderAlgorithmsKMC.py
frozenSpider/spiderAlgorithmsNB.py
frozenSpider/spiderAlgorithmsSVM.py
frozenSpider/spiderNets.py
frozenSpider/spiderNets/__init__.py
frozenSpider/spiderNets/main.py
frozenSpider/spiderNets/main1.py
frozenSpider/spiderNets/neuralNetworks.py
frozenSpider/spiderNets/temp.py
frozenSpider/spiderNets/test.py
frozenSpider/spiderNets/trial.py
frozenSpider/spiderNets/reinforcement_learning/__init__.py
frozenSpider/spiderNets/reinforcement_learning/q_learning.py
frozenSpider-0.0.7.dist-info/LICENSE.txt
frozenSpider-0.0.7.dist-info/METADATA
frozenSpider-0.0.7.dist-info/WHEEL
frozenSpider-0.0.7.dist-info/top_level.txt
frozenSpider-0.0.7.dist-info/RECORD
