Metadata-Version: 2.1
Name: frozenSpider
Version: 0.0.7
Summary: Library to implement and visualise ML Algorithms
Home-page: https://github.com/mrfrozen97
Author: mr_frozen97
Author-email: mrfrozenpeak@gmail.com
License: MIT
Keywords: ml algorithms
Platform: UNKNOWN
Classifier: Development Status :: 5 - Production/Stable
Classifier: Intended Audience :: Education
Classifier: Operating System :: Microsoft :: Windows :: Windows 10
Classifier: License :: OSI Approved :: MIT License
Classifier: Programming Language :: Python :: 3
Requires-Dist: numpy
